<?xml version="1.0" encoding="UTF-8"?>
<osmChange version="0.6" generator="openstreetmap-cgimap 2.1.0 (1765819 spike-06.openstreetmap.org)" copyright="OpenStreetMap and contributors" attribution="http://www.openstreetmap.org/copyright" license="http://opendatacommons.org/licenses/odbl/1-0/">
 <create>
  <node id="13524583301" visible="true" version="1" changeset="178103280" timestamp="2026-02-04T16:48:16Z" user="Matvey1221" uid="23788233" lat="53.7314359" lon="49.3984589"/>
 </create>
 <create>
  <node id="13524583302" visible="true" version="1" changeset="178103280" timestamp="2026-02-04T16:48:16Z" user="Matvey1221" uid="23788233" lat="53.7313876" lon="49.3984498"/>
 </create>
 <create>
  <node id="13524583303" visible="true" version="1" changeset="178103280" timestamp="2026-02-04T16:48:16Z" user="Matvey1221" uid="23788233" lat="53.7313762" lon="49.3984412"/>
 </create>
 <create>
  <node id="13524583304" visible="true" version="1" changeset="178103280" timestamp="2026-02-04T16:48:16Z" user="Matvey1221" uid="23788233" lat="53.7313726" lon="49.3985142"/>
 </create>
 <create>
  <node id="13524583305" visible="true" version="1" changeset="178103280" timestamp="2026-02-04T16:48:16Z" user="Matvey1221" uid="23788233" lat="53.7313122" lon="49.3985093"/>
 </create>
 <create>
  <node id="13524583306" visible="true" version="1" changeset="178103280" timestamp="2026-02-04T16:48:16Z" user="Matvey1221" uid="23788233" lat="53.7313139" lon="49.3984325"/>
 </create>
 <create>
  <node id="13524583307" visible="true" version="1" changeset="178103280" timestamp="2026-02-04T16:48:16Z" user="Matvey1221" uid="23788233" lat="53.7314400" lon="49.3988320"/>
 </create>
 <create>
  <node id="13524583308" visible="true" version="1" changeset="178103280" timestamp="2026-02-04T16:48:16Z" user="Matvey1221" uid="23788233" lat="53.7311534" lon="49.3987650"/>
 </create>
 <create>
  <node id="13524583309" visible="true" version="1" changeset="178103280" timestamp="2026-02-04T16:48:16Z" user="Matvey1221" uid="23788233" lat="53.7311789" lon="49.3983869"/>
 </create>
 <create>
  <node id="13524583310" visible="true" version="1" changeset="178103280" timestamp="2026-02-04T16:48:16Z" user="Matvey1221" uid="23788233" lat="53.7314705" lon="49.3984588"/>
 </create>
 <create>
  <node id="13524583311" visible="true" version="1" changeset="178103280" timestamp="2026-02-04T16:48:16Z" user="Matvey1221" uid="23788233" lat="53.7311632" lon="49.3986214"/>
 </create>
 <create>
  <node id="13524583312" visible="true" version="1" changeset="178103280" timestamp="2026-02-04T16:48:16Z" user="Matvey1221" uid="23788233" lat="53.7311645" lon="49.3986218"/>
 </create>
 <create>
  <node id="13524583313" visible="true" version="1" changeset="178103280" timestamp="2026-02-04T16:48:16Z" user="Matvey1221" uid="23788233" lat="53.7311712" lon="49.3985274"/>
 </create>
 <create>
  <node id="13524583314" visible="true" version="1" changeset="178103280" timestamp="2026-02-04T16:48:16Z" user="Matvey1221" uid="23788233" lat="53.7311962" lon="49.3985324"/>
 </create>
 <create>
  <node id="13524583315" visible="true" version="1" changeset="178103280" timestamp="2026-02-04T16:48:16Z" user="Matvey1221" uid="23788233" lat="53.7311896" lon="49.3986268"/>
 </create>
 <create>
  <node id="13524583316" visible="true" version="1" changeset="178103280" timestamp="2026-02-04T16:48:16Z" user="Matvey1221" uid="23788233" lat="53.7311850" lon="49.3986413"/>
 </create>
 <create>
  <node id="13524583317" visible="true" version="1" changeset="178103280" timestamp="2026-02-04T16:48:16Z" user="Matvey1221" uid="23788233" lat="53.7311639" lon="49.3986369"/>
 </create>
 <create>
  <node id="13524583318" visible="true" version="1" changeset="178103280" timestamp="2026-02-04T16:48:16Z" user="Matvey1221" uid="23788233" lat="53.7311556" lon="49.3987528"/>
 </create>
 <create>
  <node id="13524583319" visible="true" version="1" changeset="178103280" timestamp="2026-02-04T16:48:16Z" user="Matvey1221" uid="23788233" lat="53.7311767" lon="49.3987571"/>
 </create>
 <create>
  <node id="13524583320" visible="true" version="1" changeset="178103280" timestamp="2026-02-04T16:48:16Z" user="Matvey1221" uid="23788233" lat="53.7311985" lon="49.3986683"/>
 </create>
 <create>
  <node id="13524583321" visible="true" version="1" changeset="178103280" timestamp="2026-02-04T16:48:16Z" user="Matvey1221" uid="23788233" lat="53.7312207" lon="49.3986735"/>
 </create>
 <create>
  <node id="13524583322" visible="true" version="1" changeset="178103280" timestamp="2026-02-04T16:48:16Z" user="Matvey1221" uid="23788233" lat="53.7312129" lon="49.3987702"/>
 </create>
 <create>
  <node id="13524583323" visible="true" version="1" changeset="178103280" timestamp="2026-02-04T16:48:16Z" user="Matvey1221" uid="23788233" lat="53.7311907" lon="49.3987651"/>
 </create>
 <create>
  <node id="13524583324" visible="true" version="1" changeset="178103280" timestamp="2026-02-04T16:48:16Z" user="Matvey1221" uid="23788233" lat="53.7312548" lon="49.3984413"/>
 </create>
 <create>
  <node id="13524583325" visible="true" version="1" changeset="178103280" timestamp="2026-02-04T16:48:16Z" user="Matvey1221" uid="23788233" lat="53.7312030" lon="49.3984310"/>
 </create>
 <create>
  <node id="13524583326" visible="true" version="1" changeset="178103280" timestamp="2026-02-04T16:48:16Z" user="Matvey1221" uid="23788233" lat="53.7311999" lon="49.3984754"/>
 </create>
 <create>
  <node id="13524583327" visible="true" version="1" changeset="178103280" timestamp="2026-02-04T16:48:16Z" user="Matvey1221" uid="23788233" lat="53.7312517" lon="49.3984858"/>
 </create>
 <create>
  <way id="1474210131" visible="true" version="1" changeset="178103280" timestamp="2026-02-04T16:48:16Z" user="Matvey1221" uid="23788233">
   <nd ref="13524515208"/>
   <nd ref="13524583301"/>
   <nd ref="13524583302"/>
   <nd ref="13524515209"/>
   <nd ref="13524515208"/>
   <tag k="building" v="carport"/>
   <tag k="building:levels" v="1"/>
   <tag k="capacity" v="1"/>
   <tag k="height" v="3"/>
   <tag k="name" v="Гараж"/>
   <tag k="roof:colour" v="#939891"/>
   <tag k="roof:shape" v="flat"/>
  </way>
 </create>
 <create>
  <way id="1474210132" visible="true" version="1" changeset="178103280" timestamp="2026-02-04T16:48:16Z" user="Matvey1221" uid="23788233">
   <nd ref="13524583303"/>
   <nd ref="13524583304"/>
   <nd ref="13524583305"/>
   <nd ref="13524583306"/>
   <nd ref="13524583303"/>
   <tag k="access" v="private"/>
   <tag k="building" v="yes"/>
   <tag k="building:levels" v="1"/>
   <tag k="building:material" v="brick"/>
   <tag k="name" v="Баня"/>
   <tag k="roof:shape" v="gabled"/>
  </way>
 </create>
 <create>
  <way id="1474210133" visible="true" version="1" changeset="178103280" timestamp="2026-02-04T16:48:16Z" user="Matvey1221" uid="23788233">
   <nd ref="13524583307"/>
   <nd ref="13524583308"/>
   <nd ref="13524583311"/>
   <nd ref="13524583309"/>
   <nd ref="13524583310"/>
   <nd ref="13524583307"/>
   <tag k="name" v="Дачный участок"/>
   <tag k="place" v="plot"/>
  </way>
 </create>
 <create>
  <way id="1474210134" visible="true" version="1" changeset="178103280" timestamp="2026-02-04T16:48:16Z" user="Matvey1221" uid="23788233">
   <nd ref="13524583312"/>
   <nd ref="13524583313"/>
   <nd ref="13524583314"/>
   <nd ref="13524583315"/>
   <nd ref="13524583312"/>
   <tag k="building" v="yes"/>
   <tag k="building:levels" v="1"/>
   <tag k="height" v="2"/>
   <tag k="name" v="Летний Курятник"/>
   <tag k="roof:shape" v="flat"/>
  </way>
 </create>
 <create>
  <way id="1474210135" visible="true" version="1" changeset="178103280" timestamp="2026-02-04T16:48:16Z" user="Matvey1221" uid="23788233">
   <nd ref="13524583316"/>
   <nd ref="13524583317"/>
   <nd ref="13524583318"/>
   <nd ref="13524583319"/>
   <nd ref="13524583316"/>
   <tag k="building" v="shed"/>
   <tag k="building:levels" v="1"/>
   <tag k="height" v="2"/>
   <tag k="lockable" v="yes"/>
   <tag k="roof:shape" v="flat"/>
  </way>
 </create>
 <create>
  <way id="1474210136" visible="true" version="1" changeset="178103280" timestamp="2026-02-04T16:48:16Z" user="Matvey1221" uid="23788233">
   <nd ref="13524583320"/>
   <nd ref="13524583321"/>
   <nd ref="13524583322"/>
   <nd ref="13524583323"/>
   <nd ref="13524583320"/>
   <tag k="building" v="greenhouse"/>
   <tag k="building:levels" v="1"/>
   <tag k="height" v="2"/>
   <tag k="roof:shape" v="dome"/>
  </way>
 </create>
 <create>
  <way id="1474210137" visible="true" version="1" changeset="178103280" timestamp="2026-02-04T16:48:16Z" user="Matvey1221" uid="23788233">
   <nd ref="13524583324"/>
   <nd ref="13524583325"/>
   <nd ref="13524583326"/>
   <nd ref="13524583327"/>
   <nd ref="13524583324"/>
   <tag k="building" v="greenhouse"/>
   <tag k="building:levels" v="1"/>
   <tag k="height" v="2"/>
   <tag k="roof:shape" v="dome"/>
  </way>
 </create>
</osmChange>
